odoo9_addon_contract_commission-9.0.1.0.0-py2.7-nspkg.pth
odoo9_addon_contract_commission-9.0.1.0.0.dist-info/DESCRIPTION.rst
odoo9_addon_contract_commission-9.0.1.0.0.dist-info/METADATA
odoo9_addon_contract_commission-9.0.1.0.0.dist-info/RECORD
odoo9_addon_contract_commission-9.0.1.0.0.dist-info/WHEEL
odoo9_addon_contract_commission-9.0.1.0.0.dist-info/metadata.json
odoo9_addon_contract_commission-9.0.1.0.0.dist-info/namespace_packages.txt
odoo9_addon_contract_commission-9.0.1.0.0.dist-info/top_level.txt
odoo_addons/contract_commission/README.rst
odoo_addons/contract_commission/__init__.py
odoo_addons/contract_commission/__openerp__.py
odoo_addons/contract_commission/i18n/ca.po
odoo_addons/contract_commission/i18n/de.po
odoo_addons/contract_commission/i18n/el_GR.po
odoo_addons/contract_commission/i18n/es.po
odoo_addons/contract_commission/i18n/es_MX.po
odoo_addons/contract_commission/i18n/fr.po
odoo_addons/contract_commission/i18n/it.po
odoo_addons/contract_commission/i18n/pt_BR.po
odoo_addons/contract_commission/i18n/sl.po
odoo_addons/contract_commission/models/__init__.py
odoo_addons/contract_commission/models/analytic.py
odoo_addons/contract_commission/static/description/icon.png
odoo_addons/contract_commission/static/description/icon.svg
odoo_addons/contract_commission/tests/__init__.py
odoo_addons/contract_commission/tests/test_contract_commission.py
